LICENSE
fast_downloader_mt/__init__.py
fast_downloader_mt/main.py
fast_downloader_mt-0.1.0.dist-info/entry_points.txt
fast_downloader_mt-0.1.0.dist-info/LICENSE
fast_downloader_mt-0.1.0.dist-info/WHEEL
fast_downloader_mt-0.1.0.dist-info/METADATA
fast_downloader_mt-0.1.0.dist-info/RECORD
