Metadata-Version: 2.1
Name: fast-downloader-mt
Version: 0.1.0
Summary: Multithreaded fast downloader
Home-page: https://github.com/Kirozen/how-am-i-supposed-to
License: MIT
Author: Kirozen
Requires-Python: >=3.8,<4.0
Classifier: Environment :: Console
Classifier: License :: OSI Approved :: MIT License
Classifier: Programming Language :: Python :: 3
Classifier: Programming Language :: Python :: 3 :: Only
Classifier: Programming Language :: Python :: 3.8
Classifier: Programming Language :: Python :: 3.9
Classifier: Topic :: Communications
Classifier: Topic :: Internet
Classifier: Topic :: Terminals
Classifier: Topic :: Utilities
Requires-Dist: click (>=7.1.2,<8.0.0)
Requires-Dist: requests (>=2.24.0,<3.0.0)
Requires-Dist: rich (>=8.0.0,<9.0.0)
Project-URL: Repository, https://github.com/Kirozen/how-am-i-supposed-to
